setup.cfg
setup.py
fixnc/__init__.py
fixnc.egg-info/PKG-INFO
fixnc.egg-info/SOURCES.txt
fixnc.egg-info/dependency_links.txt
fixnc.egg-info/not-zip-safe
fixnc.egg-info/pbr.json
fixnc.egg-info/requires.txt
fixnc.egg-info/top_level.txt