Metadata-Version: 1.1
Name: fixnc
Version: 0.0.1
Summary: Easy edit of netCDF files.
Home-page: https://github.com/koldunovn/fixnc/
Author: Nikolay Koldunov
Author-email: koldunovn@gmail.com
License: MIT
Platform: UNKNOWN
Classifier: Development Status :: 3 - Alpha
Classifier: License :: OSI Approved :: MIT License
Classifier: Operating System :: OS Independent
Classifier: Intended Audience :: Science/Research
Classifier: Programming Language :: Python
Classifier: Programming Language :: Python :: 2
Classifier: Programming Language :: Python :: 2.7
Classifier: Topic :: Scientific/Engineering
